tkitBentomlFrameworksExpand/PytorchLightningArtifact.py
tkitBentomlFrameworksExpand/PytorchModelArtifact.py
tkitBentomlFrameworksExpand/TokenizerArtifact.py
tkitBentomlFrameworksExpand/__init__.py
tkitBentomlFrameworksExpand-0.0.0.216386886.dist-info/LICENSE
tkitBentomlFrameworksExpand-0.0.0.216386886.dist-info/METADATA
tkitBentomlFrameworksExpand-0.0.0.216386886.dist-info/WHEEL
tkitBentomlFrameworksExpand-0.0.0.216386886.dist-info/top_level.txt
tkitBentomlFrameworksExpand-0.0.0.216386886.dist-info/RECORD
