Metadata-Version: 2.1
Name: tkitBentomlFrameworksExpand
Version: 0.0.0.216386886
Summary: Terry toolkit tkit-bentoml-tkitBentomlFrameworksExpand-expand,
Home-page: https://github.com/napoler/tkit-bentoml-frameworks-expand
Author: Terry Chan
Author-email: napoler2008@gmail.com
License: UNKNOWN
Platform: UNKNOWN
